ara_core/__init__.py
ara_core/app.py
ara_core/exceptions.py
ara_core-1.1.1.dist-info/METADATA
ara_core-1.1.1.dist-info/WHEEL
ara_core-1.1.1.dist-info/top_level.txt
ara_core-1.1.1.dist-info/RECORD
