Metadata-Version: 2.4
Name: Ara_core
Version: 1.1.1
Summary: Lightweight minimalistic Ara framework
Author-email: HanamileH <hanamileh@gmail.com>
License-Expression: MIT
Project-URL: Homepage, https://github.com/hanamileh-DEV/Ara_core
Requires-Python: >=3.8
Requires-Dist: glfw>=2.8.0
Requires-Dist: pyopengl>=3.1.9
Requires-Dist: ara_log>=1.0.0
